snpfilter/__init__.py
snpfilter/cli.py
snpfilter/versions.py
snpfilter/scripts/__init__.py
snpfilter/scripts/map.py
SNPfilter-0.0.5.dist-info/LICENSE
SNPfilter-0.0.5.dist-info/METADATA
SNPfilter-0.0.5.dist-info/WHEEL
SNPfilter-0.0.5.dist-info/entry_points.txt
SNPfilter-0.0.5.dist-info/top_level.txt
SNPfilter-0.0.5.dist-info/RECORD
