Metadata-Version: 2.1
Name: SNPfilter
Version: 0.0.5
Summary: A handy little tool for filtering SNPs.
Home-page: https://github.com/SouthernCD/SNPfilter
Author: Yuxing Xu
Author-email: xuyuxing@mail.kib.ac.cn
License: UNKNOWN
Platform: UNKNOWN
Requires-Python: >=3.5
License-File: LICENSE
Requires-Dist: pysam (>=0.21.0)
Requires-Dist: toolbiox (>=0.0.39)
